pylob/__init__.py
pylob/consts/__init__.py
pylob/consts/consts.py
pylob/engine/__init__.py
pylob/engine/engine.py
pylob/enums/__init__.py
pylob/enums/enums.py
pylob/limit/__init__.py
pylob/limit/limit.py
pylob/order/__init__.py
pylob/order/order.py
pylob/order/params.py
pylob/orderbook/__init__.py
pylob/orderbook/orderbook.py
pylob/orderbook/result.py
pylob/side/__init__.py
pylob/side/side.py
pylob/utils/__init__.py
pylob/utils/utils.py
fastlob-0.1.0.dist-info/METADATA
fastlob-0.1.0.dist-info/WHEEL
fastlob-0.1.0.dist-info/top_level.txt
fastlob-0.1.0.dist-info/RECORD
