Metadata-Version: 2.2
Name: fastlob
Version: 0.1.0
Author-email: Maxime Rochkoulets <mrochkoulets@gmail.com>
Project-URL: Homepage, https://github.com/mrochk/pylob
Requires-Python: >=3.6
Requires-Dist: sortedcollections==2.1.0
